paint.py
term_paint2-1.0.0.dist-info/METADATA
term_paint2-1.0.0.dist-info/WHEEL
term_paint2-1.0.0.dist-info/entry_points.txt
term_paint2-1.0.0.dist-info/top_level.txt
term_paint2-1.0.0.dist-info/RECORD
